errors/__init__.py
stdexcept/__init__.py
stdexcept/errors/__init__.py
stdexcept-0.1.0.dist-info/LICENSE
stdexcept-0.1.0.dist-info/METADATA
stdexcept-0.1.0.dist-info/WHEEL
stdexcept-0.1.0.dist-info/top_level.txt
stdexcept-0.1.0.dist-info/RECORD
