Metadata-Version: 2.1
Name: stdexcept
Version: 0.1.0
Summary: Terminal Raise Error Tools
Home-page: https://pymodule.rsc-studio.com/stdexcept
Author: RSC-E Studio
Author-email: rscestudio114514@gmail.com
License: MIT
Keywords: output,stdout,stderr,suppress,mute,silence
Classifier: License :: OSI Approved :: MIT License
Classifier: Programming Language :: Python :: 3
Classifier: Programming Language :: Python :: 3.7
Classifier: Programming Language :: Python :: 3.8
Classifier: Programming Language :: Python :: 3.9
Classifier: Programming Language :: Python :: 3.10
Classifier: Programming Language :: Python :: 3.11
Classifier: Operating System :: OS Independent
Classifier: Topic :: Software Development :: Libraries
Classifier: Topic :: Utilities
Requires-Python: >=3.7
License-File: LICENSE
